README.md
setup.py
DeWave/__init__.py
DeWave/audiopacker.py
DeWave/audioreader.py
DeWave/clip.py
DeWave/cmddatapack.py
DeWave/cmddataprep.py
DeWave/cmdinfer.py
DeWave/cmdtrain.py
DeWave/constant.py
DeWave/datagenerator.py
DeWave/evaluate.py
DeWave/infer.py
DeWave/model.py
DeWave/train.py
DeWave/utility.py
DeWave.egg-info/PKG-INFO
DeWave.egg-info/SOURCES.txt
DeWave.egg-info/dependency_links.txt
DeWave.egg-info/entry_points.txt
DeWave.egg-info/not-zip-safe
DeWave.egg-info/requires.txt
DeWave.egg-info/top_level.txt