Metadata-Version: 1.1
Name: DeWave
Version: 0.12
Summary: Single-channel blind source separation
Home-page: https://github.com/chaodengusc/DeWave
Author: Chao Deng
Author-email: chaodengusc@gmail.com
License: MIT
Keywords: Blind source separation,Single channel
Platform: UNKNOWN
Classifier: Development Status :: 3 - Alpha
Classifier: License :: OSI Approved :: MIT License
Classifier: Programming Language :: Python :: 3.6
Classifier: Topic :: Software Development :: Build Tools
